torappu_excel/__init__.py
torappu_excel/common.py
torappu_excel/constants.py
torappu_excel/models.py
torappu_excel/py.typed
torappu_excel/utils.py
torappu_excel/json/activity_table.json
torappu_excel/json/audio_data.json
torappu_excel/json/battle_equip_table.json
torappu_excel/json/building_data.json
torappu_excel/json/campaign_table.json
torappu_excel/json/chapter_table.json
torappu_excel/json/char_master_table.json
torappu_excel/json/char_meta_table.json
torappu_excel/json/char_patch_table.json
torappu_excel/json/character_table.json
torappu_excel/json/charm_table.json
torappu_excel/json/charword_table.json
torappu_excel/json/checkin_table.json
torappu_excel/json/climb_tower_table.json
torappu_excel/json/clue_data.json
torappu_excel/json/crisis_table.json
torappu_excel/json/crisis_v2_table.json
torappu_excel/json/data_version.txt
torappu_excel/json/display_meta_table.json
torappu_excel/json/enemy_handbook_table.json
torappu_excel/json/favor_table.json
torappu_excel/json/gacha_table.json
torappu_excel/json/gamedata_const.json
torappu_excel/json/handbook_info_table.json
torappu_excel/json/handbook_table.json
torappu_excel/json/handbook_team_table.json
torappu_excel/json/hotupdate_meta_table.json
torappu_excel/json/init_text.json
torappu_excel/json/item_table.json
torappu_excel/json/main_text.json
torappu_excel/json/medal_table.json
torappu_excel/json/meta_ui_table.json
torappu_excel/json/mission_table.json
torappu_excel/json/open_server_table.json
torappu_excel/json/player_avatar_table.json
torappu_excel/json/range_table.json
torappu_excel/json/replicate_table.json
torappu_excel/json/retro_table.json
torappu_excel/json/roguelike_table.json
torappu_excel/json/roguelike_topic_table.json
torappu_excel/json/sandbox_perm_table.json
torappu_excel/json/sandbox_table.json
torappu_excel/json/shop_client_table.json
torappu_excel/json/skill_table.json
torappu_excel/json/skin_table.json
torappu_excel/json/special_operator_table.json
torappu_excel/json/stage_table.json
torappu_excel-2.6.82.dist-info/METADATA
torappu_excel-2.6.82.dist-info/WHEEL
torappu_excel-2.6.82.dist-info/licenses/LICENSE
torappu_excel-2.6.82.dist-info/RECORD
