Metadata-Version: 2.4
Name: torappu-excel
Version: 2.6.82
Summary: Torappu Client Excel Model Library
Author: DICE_Lab
Author-email: baiqwerdvd <baiqwerdvd@gmail.com>
License: MIT License
License-File: LICENSE
Requires-Python: <3.15,>=3.11
Requires-Dist: aiofiles>=25.1.0
Requires-Dist: aiohttp>=3.13.2
Requires-Dist: msgspec>=0.20.0
Requires-Dist: typing-extensions>=4.15.0
